[{"name":"Juanes","nextPha":9,"firstGroup":2,"secondGroup":2,"scores":0,"numGoals":2,"firstPos":0,"secondPos":0,"thirdPos":1,"quarter":0,"total":135},
{"name":"Harvi","nextPha":8,"firstGroup":2,"secondGroup":1,"scores":0,"numGoals":1,"firstPos":0,"secondPos":0,"thirdPos":1,"quarter":0,"total":115},
{"name":"Cristian","nextPha":9,"firstGroup":1,"secondGroup":2,"scores":0,"numGoals":0,"firstPos":0,"secondPos":0,"thirdPos":1,"quarter":0,"total":120},
{"name":"Eduar","nextPha":7,"firstGroup":2,"secondGroup":0,"scores":0,"numGoals":0,"firstPos":0,"secondPos":0,"thirdPos":1,"quarter":0,"total":95},
{"name":"Luis Eduardo","nextPha":8,"firstGroup":2,"secondGroup":2,"scores":0,"numGoals":2,"firstPos":0,"secondPos":0,"thirdPos":1,"quarter":0,"total":125},
{"name":"Santiago","nextPha":8,"firstGroup":2,"secondGroup":2,"scores":0,"numGoals":1,"firstPos":0,"secondPos":0,"thirdPos":1,"quarter":0,"total":120},
{"name":"Daniel Cano","nextPha":7,"firstGroup":2,"secondGroup":2,"scores":0,"numGoals":0,"firstPos":0,"secondPos":0,"thirdPos":0,"quarter":0,"total":90},
{"name":"Astrid","nextPha":9,"firstGroup":3,"secondGroup":2,"scores":0,"numGoals":0,"firstPos":0,"secondPos":0,"thirdPos":0,"quarter":0,"total":115},
{"name":"Gloria","nextPha":10,"firstGroup":2,"secondGroup":2,"scores":0,"numGoals":1,"firstPos":0,"secondPos":0,"thirdPos":1,"quarter":0,"total":140},
{"name":"Juan","nextPha":9,"firstGroup":1,"secondGroup":1,"scores":0,"numGoals":1,"firstPos":0,"secondPos":0,"thirdPos":0,"quarter":0,"total":105},
{"name":"Frisky","nextPha":7,"firstGroup":2,"secondGroup":2,"scores":0,"numGoals":1,"firstPos":0,"secondPos":0,"thirdPos":0,"quarter":0,"total":95},
{"name":"Andres R.","nextPha":8,"firstGroup":2,"secondGroup":2,"scores":0,"numGoals":1,"firstPos":0,"secondPos":0,"thirdPos":0,"quarter":0,"total":105},
{"name":"Juliana","nextPha":7,"firstGroup":2,"secondGroup":2,"scores":0,"numGoals":1,"firstPos":0,"secondPos":0,"thirdPos":0,"quarter":0,"total":95},
{"name":"Felipe","nextPha":10,"firstGroup":3,"secondGroup":1,"scores":0,"numGoals":2,"firstPos":0,"secondPos":0,"thirdPos":1,"quarter":0,"total":145},
{"name":"Maldonado","nextPha":9,"firstGroup":2,"secondGroup":2,"scores":0,"numGoals":0,"firstPos":0,"secondPos":0,"thirdPos":0,"quarter":0,"total":110},
{"name":"Diomer","nextPha":9,"firstGroup":2,"secondGroup":2,"scores":0,"numGoals":1,"firstPos":0,"secondPos":0,"thirdPos":0,"quarter":0,"total":115},
{"name":"Viviana","nextPha":8,"firstGroup":2,"secondGroup":2,"scores":0,"numGoals":1,"firstPos":0,"secondPos":0,"thirdPos":0,"quarter":0,"total":105},
{"name":"Andres B.","nextPha":9,"firstGroup":2,"secondGroup":2,"scores":0,"numGoals":0,"firstPos":0,"secondPos":0,"thirdPos":1,"quarter":0,"total":125},
{"name":"Esneider","nextPha":10,"firstGroup":2,"secondGroup":2,"scores":0,"numGoals":2,"firstPos":0,"secondPos":0,"thirdPos":0,"quarter":0,"total":130},
{"name":"Gabriel Juju","nextPha":8,"firstGroup":2,"secondGroup":1,"scores":0,"numGoals":0,"firstPos":0,"secondPos":0,"thirdPos":1,"quarter":0,"total":110},
{"name":"Juanda","nextPha":8,"firstGroup":2,"secondGroup":2,"scores":0,"numGoals":0,"firstPos":0,"secondPos":0,"thirdPos":0,"quarter":0,"total":100}]